minrest/__init__.py
minrest/minrest.py
minrest/parser.py
minrest-0.1.1.dist-info/AUTHORS.rst
minrest-0.1.1.dist-info/LICENSE
minrest-0.1.1.dist-info/METADATA
minrest-0.1.1.dist-info/WHEEL
minrest-0.1.1.dist-info/top_level.txt
minrest-0.1.1.dist-info/RECORD
