Metadata-Version: 2.1
Name: minrest
Version: 0.1.1
Summary: Minimalistic generic REST API client for Python
Home-page: https://github.com/leonardodiegues/minrest
Author: Leonardo Diegues
Author-email: dscleo@gmail.com
License: MIT license
Keywords: minrest
Platform: UNKNOWN
Classifier: Development Status :: 2 - Pre-Alpha
Classifier: Intended Audience :: Developers
Classifier: License :: OSI Approved :: MIT License
Classifier: Natural Language :: English
Classifier: Programming Language :: Python :: 3
Classifier: Programming Language :: Python :: 3.5
Classifier: Programming Language :: Python :: 3.6
Classifier: Programming Language :: Python :: 3.7
Classifier: Programming Language :: Python :: 3.8
Requires-Python: >=3.5
Requires-Dist: requests
Requires-Dist: pandas
